juliangip/Juliang.py
juliangip/__init__.py
juliangip/common/AloneGetIps.py
juliangip/common/AloneGetWhiteIp.py
juliangip/common/AloneReplaceWhiteIp.py
juliangip/common/AloneSetWhiteIp.py
juliangip/common/CompanyDynamicDelWhiteIp.py
juliangip/common/CompanyDynamicGetIps.py
juliangip/common/CompanyDynamicGetWhiteIp.py
juliangip/common/CompanyDynamicSetWhiteIp.py
juliangip/common/CompanyPostPayDelWhiteIp.py
juliangip/common/CompanyPostPayGetIps.py
juliangip/common/CompanyPostPayGetWhiteIp.py
juliangip/common/CompanyPostPaySetWhiteIp.py
juliangip/common/DynamicBalance.py
juliangip/common/DynamicCheck.py
juliangip/common/DynamicGetIps.py
juliangip/common/DynamicGetWhiteIp.py
juliangip/common/DynamicRemain.py
juliangip/common/DynamicReplaceWhiteIp.py
juliangip/common/DynamicSetWhiteIp.py
juliangip/common/PostPayCheck.py
juliangip/common/PostPayGetIps.py
juliangip/common/PostPayGetWhiteIp.py
juliangip/common/PostPayReplaceWhiteIp.py
juliangip/common/PostPaySetWhiteIp.py
juliangip/common/UnlimitedGetIps.py
juliangip/common/UnlimitedGetWhiteIp.py
juliangip/common/UnlimitedReplaceWhiteIp.py
juliangip/common/UnlimitedSetWhiteIp.py
juliangip/common/UsersGetAllOrders.py
juliangip/common/UsersGetBalance.py
juliangip/common/UsersGetCity.py
juliangip/common/__init__.py
juliangip/enums/URL.py
juliangip/enums/__init__.py
juliangip/ext/StrKit.py
juliangip/ext/__init__.py
juliang-1.2.0.dist-info/METADATA
juliang-1.2.0.dist-info/WHEEL
juliang-1.2.0.dist-info/top_level.txt
juliang-1.2.0.dist-info/RECORD
